{
  "aliases": [],
  "contentHash": "57b87420fc13bb68374fb9b9297c192f622b749e726bd1bb466c590df4db1b3f",
  "domain": "CHARACTER",
  "entityType": "character",
  "gradeEnd": 2,
  "gradeStart": 1,
  "id": "cn-chn-item-character-u81ea",
  "licenseClass": "CC-BY-4.0",
  "originRepositoryId": "cn-primary-chinese-taxonomy",
  "schemaVersion": "1.0",
  "sourceRefs": [
    "source-moe-chinese-curriculum-2022"
  ],
  "subject": "chinese",
  "summary": "## 内容属性\n\n{\"strokeCount\":6,\"writtenForm\":\"自\"}\n\n## 证据线\n\n- CURRICULUM_STANDARD",
  "title": "自"
}
