{
  "aliases": [],
  "contentHash": "858dc7ee512f8409515d98829990c37bd38c37aa79476dbd3c751fffac76f5ac",
  "domain": "CHARACTER",
  "entityType": "character",
  "gradeEnd": 2,
  "gradeStart": 1,
  "id": "cn-chn-item-character-u5b50",
  "licenseClass": "CC-BY-4.0",
  "originRepositoryId": "cn-primary-chinese-taxonomy",
  "schemaVersion": "1.0",
  "sourceRefs": [
    "source-moe-chinese-curriculum-2022"
  ],
  "subject": "chinese",
  "summary": "## 内容属性\n\n{\"strokeCount\":3,\"writtenForm\":\"子\"}\n\n## 证据线\n\n- CURRICULUM_STANDARD",
  "title": "子"
}
